gif2xls/__init__.py
gif2xls/__main__.py
gif2xls/boring.py
gif2xls/colours.py
gif2xls/common.py
gif2xls/fancy.py
gif2xls/version.py
gif2xls-0.2.2.dist-info/DESCRIPTION.rst
gif2xls-0.2.2.dist-info/METADATA
gif2xls-0.2.2.dist-info/RECORD
gif2xls-0.2.2.dist-info/WHEEL
gif2xls-0.2.2.dist-info/entry_points.txt
gif2xls-0.2.2.dist-info/metadata.json
gif2xls-0.2.2.dist-info/top_level.txt
