Metadata-Version: 2.0
Name: gif2xls
Version: 0.2.2
Summary: Convert GIF images into XLS files.
Home-page: https://github.com/bell345/gif2xls
Author: Thomas Bell
Author-email: tom.aus@outlook.com
License: MIT
Keywords: xls gif convert xkcd
Platform: UNKNOWN
Classifier: Development Status :: 3 - Alpha
Classifier: License :: OSI Approved :: MIT License
Classifier: Programming Language :: Python :: 2
Classifier: Programming Language :: Python :: 2.6
Classifier: Programming Language :: Python :: 2.7
Classifier: Programming Language :: Python :: 3
Classifier: Programming Language :: Python :: 3.3
Classifier: Programming Language :: Python :: 3.4
Classifier: Programming Language :: Python :: 3.5
Classifier: Topic :: Multimedia :: Graphics :: Graphics Conversion
Classifier: Topic :: Office/Business :: Financial :: Spreadsheet
Requires-Dist: Pillow (>=3.0)
Requires-Dist: XlsxWriter (>=0.8)
Requires-Dist: future (>=0.15)
Requires-Dist: pyexcel (>=0.2)
Requires-Dist: pyexcel-xls (>=0.1)
Requires-Dist: pyexcel-xlsx (>=0.1)
Requires-Dist: xlwt (>=1.0)
